WeiYewuliangShenDazaoAliWenyuYonghuJiNeirongYunyingPingtaiJishuShijianFix1/README.md
WeiYewuliangShenDazaoAliWenyuYonghuJiNeirongYunyingPingtaiJishuShijianFix1/__init__.py
WeiYewuliangShenDazaoAliWenyuYonghuJiNeirongYunyingPingtaiJishuShijianFix1/__main__.py
WeiYewuliangShenDazaoAliWenyuYonghuJiNeirongYunyingPingtaiJishuShijianFix1/file.pdf
WeiYewuliangShenDazaoAliWenyuYonghuJiNeirongYunyingPingtaiJishuShijianFix1/index.html
wei_yewuliang_shen_dazao_ali_wenyu_yonghu_ji_neirong_yunying_pingtai_jishu_shijian_fix1-2025.3.25.1.dist-info/METADATA
wei_yewuliang_shen_dazao_ali_wenyu_yonghu_ji_neirong_yunying_pingtai_jishu_shijian_fix1-2025.3.25.1.dist-info/WHEEL
wei_yewuliang_shen_dazao_ali_wenyu_yonghu_ji_neirong_yunying_pingtai_jishu_shijian_fix1-2025.3.25.1.dist-info/entry_points.txt
wei_yewuliang_shen_dazao_ali_wenyu_yonghu_ji_neirong_yunying_pingtai_jishu_shijian_fix1-2025.3.25.1.dist-info/top_level.txt
wei_yewuliang_shen_dazao_ali_wenyu_yonghu_ji_neirong_yunying_pingtai_jishu_shijian_fix1-2025.3.25.1.dist-info/RECORD
